niaaml/__init__.py
niaaml/classifiers/__init__.py
niaaml/classifiers/ada_boost.py
niaaml/classifiers/bagging.py
niaaml/classifiers/classifier.py
niaaml/classifiers/decision_tree.py
niaaml/classifiers/extremely_randomized_trees.py
niaaml/classifiers/gaussian_naive_bayes.py
niaaml/classifiers/gaussian_process.py
niaaml/classifiers/k_neighbors.py
niaaml/classifiers/linear_svc.py
niaaml/classifiers/multi_layer_perceptron.py
niaaml/classifiers/quadratic_driscriminant_analysis.py
niaaml/classifiers/random_forest.py
niaaml/classifiers/regression_decision_tree.py
niaaml/classifiers/regression_gaussian_process.py
niaaml/classifiers/regression_lasso.py
niaaml/classifiers/regression_linear_model.py
niaaml/classifiers/regression_ridge.py
niaaml/classifiers/utility.py
niaaml/cli.py
niaaml/data/__init__.py
niaaml/data/basic_data_reader.py
niaaml/data/csv_data_reader.py
niaaml/data/data_reader.py
niaaml/fitness/__init__.py
niaaml/fitness/accuracy.py
niaaml/fitness/cohen_kappa.py
niaaml/fitness/f1.py
niaaml/fitness/fitness_function.py
niaaml/fitness/mse.py
niaaml/fitness/precision.py
niaaml/fitness/r2.py
niaaml/fitness/utility.py
niaaml/logger.py
niaaml/pipeline.py
niaaml/pipeline_component.py
niaaml/pipeline_optimizer.py
niaaml/preprocessing/__init__.py
niaaml/preprocessing/encoding/__init__.py
niaaml/preprocessing/encoding/feature_encoder.py
niaaml/preprocessing/encoding/one_hot_encoder.py
niaaml/preprocessing/encoding/utility.py
niaaml/preprocessing/feature_selection/__init__.py
niaaml/preprocessing/feature_selection/_feature_selection_threshold_problem.py
niaaml/preprocessing/feature_selection/bat_algorithm.py
niaaml/preprocessing/feature_selection/differential_evolution.py
niaaml/preprocessing/feature_selection/feature_selection_algorithm.py
niaaml/preprocessing/feature_selection/grey_wolf_optimizer.py
niaaml/preprocessing/feature_selection/jDEFSTH.py
niaaml/preprocessing/feature_selection/particle_swarm_optimization.py
niaaml/preprocessing/feature_selection/select_k_best.py
niaaml-2.2.0.dist-info/LICENSE
niaaml-2.2.0.dist-info/METADATA
niaaml-2.2.0.dist-info/WHEEL
niaaml-2.2.0.dist-info/entry_points.txt
niaaml-2.2.0.dist-info/RECORD
