Metadata-Version: 2.3
Name: NiaAML
Version: 2.2.0
Summary: Python automated machine learning framework
License: MIT
Keywords: classification,NiaPy,scikit-learn,nature-inspired algorithms,feature selection,preprocessing
Author: Luka Pečnik
Author-email: lukapecnik96@gmail.com
Requires-Python: >=3.10,<=3.14
Classifier: License :: OSI Approved :: MIT License
Classifier: Programming Language :: Python :: 3
Classifier: Programming Language :: Python :: 3.10
Classifier: Programming Language :: Python :: 3.11
Classifier: Programming Language :: Python :: 3.12
Classifier: Programming Language :: Python :: 3.13
Requires-Dist: loguru (>=0.7.2,<0.8.0)
Requires-Dist: niapy (>=2.6.1,<3.0.0)
Requires-Dist: numpy (>=2.1.1,<3.0.0)
Requires-Dist: pandas (>=2.1.1,<3.0.0)
Requires-Dist: scikit-learn (>=1.6.1,<2.0.0)
Requires-Dist: typer (>=0.12.3,<0.13.0)
Project-URL: Documentation, https://niaaml.readthedocs.io/en/latest/
Project-URL: Homepage, https://github.com/firefly-cpp/NiaAML
Project-URL: Repository, https://github.com/firefly-cpp/NiaAML
